JoyVis/JoyVis.py
JoyVis/__init__.py
JoyVis/example.py
joyvis-1.1.0.dist-info/METADATA
joyvis-1.1.0.dist-info/WHEEL
joyvis-1.1.0.dist-info/top_level.txt
joyvis-1.1.0.dist-info/RECORD
