Metadata-Version: 2.1
Name: joyvis
Version: 1.1.0
Summary: RDF Visualization for SPARQL Endpoint and local file
Home-page: https://joyhong.tistory.com
Author: joyhong
Author-email: su4620@gmail.com
License: MIT
Project-URL: Source Code, https://github.com/joyhong85/JoyVis
Platform: UNKNOWN
Classifier: Framework :: Jupyter
Classifier: Programming Language :: Python :: 3.6
Classifier: Topic :: Scientific/Engineering :: Artificial Intelligence
Classifier: Topic :: Scientific/Engineering :: Visualization
Classifier: Topic :: Software Development :: Libraries :: Python Modules
Classifier: Topic :: Software Development :: Version Control :: Git
Requires-Python: >=3
Requires-Dist: pyvis
Requires-Dist: rdflib (==7.0.0)
Requires-Dist: SPARQLWrapper (==2.0.0)
